alibabacloud_push20160801/__init__.py
alibabacloud_push20160801/client.py
alibabacloud_push20160801/models/__init__.py
alibabacloud_push20160801/models/_bind_alias_request.py
alibabacloud_push20160801/models/_bind_alias_response.py
alibabacloud_push20160801/models/_bind_alias_response_body.py
alibabacloud_push20160801/models/_bind_phone_request.py
alibabacloud_push20160801/models/_bind_phone_response.py
alibabacloud_push20160801/models/_bind_phone_response_body.py
alibabacloud_push20160801/models/_bind_tag_request.py
alibabacloud_push20160801/models/_bind_tag_response.py
alibabacloud_push20160801/models/_bind_tag_response_body.py
alibabacloud_push20160801/models/_cancel_push_request.py
alibabacloud_push20160801/models/_cancel_push_response.py
alibabacloud_push20160801/models/_cancel_push_response_body.py
alibabacloud_push20160801/models/_check_certificate_request.py
alibabacloud_push20160801/models/_check_certificate_response.py
alibabacloud_push20160801/models/_check_certificate_response_body.py
alibabacloud_push20160801/models/_check_device_request.py
alibabacloud_push20160801/models/_check_device_response.py
alibabacloud_push20160801/models/_check_device_response_body.py
alibabacloud_push20160801/models/_check_devices_request.py
alibabacloud_push20160801/models/_check_devices_response.py
alibabacloud_push20160801/models/_check_devices_response_body.py
alibabacloud_push20160801/models/_complete_continuously_push_request.py
alibabacloud_push20160801/models/_complete_continuously_push_response.py
alibabacloud_push20160801/models/_complete_continuously_push_response_body.py
alibabacloud_push20160801/models/_continuously_push_request.py
alibabacloud_push20160801/models/_continuously_push_response.py
alibabacloud_push20160801/models/_continuously_push_response_body.py
alibabacloud_push20160801/models/_list_summary_apps_response.py
alibabacloud_push20160801/models/_list_summary_apps_response_body.py
alibabacloud_push20160801/models/_list_tags_request.py
alibabacloud_push20160801-2.1.3.dist-info/LICENSE
alibabacloud_push20160801-2.1.3.dist-info/METADATA
alibabacloud_push20160801-2.1.3.dist-info/WHEEL
alibabacloud_push20160801-2.1.3.dist-info/top_level.txt
alibabacloud_push20160801-2.1.3.dist-info/RECORD
